{
  "version": "sprite-v1-2026-05-04T19:44:09.839Z",
  "cellSize": 64,
  "imagePath": "atlas.png",
  "frames": {
    "tile.space": {
      "x": 2,
      "y": 2,
      "w": 256,
      "h": 256
    },
    "tile.floor": {
      "x": 262,
      "y": 2,
      "w": 64,
      "h": 64
    },
    "tile.wall": {
      "x": 330,
      "y": 2,
      "w": 64,
      "h": 64
    },
    "tile.wall.solo": {
      "x": 398,
      "y": 2,
      "w": 64,
      "h": 64
    },
    "tile.wall.end": {
      "x": 466,
      "y": 2,
      "w": 64,
      "h": 64
    },
    "tile.wall.straight": {
      "x": 534,
      "y": 2,
      "w": 64,
      "h": 64
    },
    "tile.wall.straight.vertical": {
      "x": 602,
      "y": 2,
      "w": 64,
      "h": 64
    },
    "tile.wall.corner": {
      "x": 670,
      "y": 2,
      "w": 64,
      "h": 64
    },
    "tile.wall.tee": {
      "x": 738,
      "y": 2,
      "w": 64,
      "h": 64
    },
    "tile.wall.cross": {
      "x": 806,
      "y": 2,
      "w": 64,
      "h": 64
    },
    "tile.wall.dt.empty": {
      "x": 874,
      "y": 2,
      "w": 64,
      "h": 64
    },
    "tile.wall.dt.single_corner": {
      "x": 942,
      "y": 2,
      "w": 64,
      "h": 64
    },
    "tile.wall.dt.edge": {
      "x": 1010,
      "y": 2,
      "w": 64,
      "h": 64
    },
    "tile.wall.dt.saddle": {
      "x": 1078,
      "y": 2,
      "w": 64,
      "h": 64
    },
    "tile.wall.dt.inner_corner": {
      "x": 1146,
      "y": 2,
      "w": 64,
      "h": 64
    },
    "tile.wall.dt.full": {
      "x": 1214,
      "y": 2,
      "w": 64,
      "h": 64
    },
    "tile.dock": {
      "x": 1282,
      "y": 2,
      "w": 64,
      "h": 64
    },
    "tile.cafeteria": {
      "x": 1350,
      "y": 2,
      "w": 64,
      "h": 64
    },
    "tile.reactor": {
      "x": 1418,
      "y": 2,
      "w": 64,
      "h": 64
    },
    "tile.security": {
      "x": 1486,
      "y": 2,
      "w": 64,
      "h": 64
    },
    "tile.door": {
      "x": 1554,
      "y": 2,
      "w": 64,
      "h": 64
    },
    "tile.airlock": {
      "x": 1622,
      "y": 2,
      "w": 64,
      "h": 64
    },
    "tile.door.horizontal": {
      "x": 1690,
      "y": 2,
      "w": 64,
      "h": 64
    },
    "tile.door.vertical": {
      "x": 1758,
      "y": 2,
      "w": 64,
      "h": 64
    },
    "room.bridge": {
      "x": 1826,
      "y": 2,
      "w": 64,
      "h": 64
    },
    "room.cafeteria": {
      "x": 1894,
      "y": 2,
      "w": 64,
      "h": 64
    },
    "room.kitchen": {
      "x": 1962,
      "y": 2,
      "w": 64,
      "h": 64
    },
    "room.workshop": {
      "x": 2030,
      "y": 2,
      "w": 64,
      "h": 64
    },
    "room.clinic": {
      "x": 2098,
      "y": 2,
      "w": 64,
      "h": 64
    },
    "room.brig": {
      "x": 2166,
      "y": 2,
      "w": 64,
      "h": 64
    },
    "room.rec_hall": {
      "x": 2234,
      "y": 2,
      "w": 64,
      "h": 64
    },
    "room.reactor": {
      "x": 2302,
      "y": 2,
      "w": 64,
      "h": 64
    },
    "room.security": {
      "x": 2370,
      "y": 2,
      "w": 64,
      "h": 64
    },
    "room.dorm": {
      "x": 2438,
      "y": 2,
      "w": 64,
      "h": 64
    },
    "room.hygiene": {
      "x": 2506,
      "y": 2,
      "w": 64,
      "h": 64
    },
    "room.hydroponics": {
      "x": 2574,
      "y": 2,
      "w": 64,
      "h": 64
    },
    "room.life_support": {
      "x": 2642,
      "y": 2,
      "w": 64,
      "h": 64
    },
    "room.lounge": {
      "x": 2710,
      "y": 2,
      "w": 64,
      "h": 64
    },
    "room.market": {
      "x": 2778,
      "y": 2,
      "w": 64,
      "h": 64
    },
    "room.logistics_stock": {
      "x": 2846,
      "y": 2,
      "w": 64,
      "h": 64
    },
    "room.storage": {
      "x": 2914,
      "y": 2,
      "w": 64,
      "h": 64
    },
    "module.none": {
      "x": 2982,
      "y": 2,
      "w": 64,
      "h": 64
    },
    "module.wall_light": {
      "x": 2,
      "y": 262,
      "w": 64,
      "h": 32
    },
    "module.bed": {
      "x": 70,
      "y": 262,
      "w": 128,
      "h": 64
    },
    "module.table": {
      "x": 202,
      "y": 262,
      "w": 128,
      "h": 128
    },
    "module.serving_station": {
      "x": 334,
      "y": 262,
      "w": 128,
      "h": 64
    },
    "module.stove": {
      "x": 466,
      "y": 262,
      "w": 128,
      "h": 64
    },
    "module.workbench": {
      "x": 598,
      "y": 262,
      "w": 128,
      "h": 64
    },
    "module.med_bed": {
      "x": 730,
      "y": 262,
      "w": 128,
      "h": 64
    },
    "module.cell_console": {
      "x": 862,
      "y": 262,
      "w": 64,
      "h": 64
    },
    "module.rec_unit": {
      "x": 930,
      "y": 262,
      "w": 128,
      "h": 128
    },
    "module.grow_station": {
      "x": 1062,
      "y": 262,
      "w": 128,
      "h": 128
    },
    "module.terminal": {
      "x": 1194,
      "y": 262,
      "w": 64,
      "h": 64
    },
    "module.bridge.captain_console": {
      "x": 1262,
      "y": 262,
      "w": 64,
      "h": 64
    },
    "module.bridge.sanitation_terminal": {
      "x": 1330,
      "y": 262,
      "w": 64,
      "h": 64
    },
    "module.bridge.security_terminal": {
      "x": 1398,
      "y": 262,
      "w": 64,
      "h": 64
    },
    "module.bridge.mechanical_terminal": {
      "x": 1466,
      "y": 262,
      "w": 64,
      "h": 64
    },
    "module.bridge.industrial_terminal": {
      "x": 1534,
      "y": 262,
      "w": 64,
      "h": 64
    },
    "module.bridge.navigation_terminal": {
      "x": 1602,
      "y": 262,
      "w": 64,
      "h": 64
    },
    "module.bridge.comms_terminal": {
      "x": 1670,
      "y": 262,
      "w": 64,
      "h": 64
    },
    "module.bridge.medical_terminal": {
      "x": 1738,
      "y": 262,
      "w": 64,
      "h": 64
    },
    "module.bridge.research_terminal": {
      "x": 1806,
      "y": 262,
      "w": 64,
      "h": 64
    },
    "module.bridge.logistics_terminal": {
      "x": 1874,
      "y": 262,
      "w": 64,
      "h": 64
    },
    "module.bridge.fleet_command_terminal": {
      "x": 1942,
      "y": 262,
      "w": 64,
      "h": 64
    },
    "module.bridge.traffic_control_terminal": {
      "x": 2010,
      "y": 262,
      "w": 64,
      "h": 64
    },
    "module.bridge.resource_management_terminal": {
      "x": 2078,
      "y": 262,
      "w": 64,
      "h": 64
    },
    "module.bridge.power_management_terminal": {
      "x": 2146,
      "y": 262,
      "w": 64,
      "h": 64
    },
    "module.bridge.life_support_terminal": {
      "x": 2214,
      "y": 262,
      "w": 64,
      "h": 64
    },
    "module.bridge.atmosphere_control_terminal": {
      "x": 2282,
      "y": 262,
      "w": 64,
      "h": 64
    },
    "module.bridge.ai_core_terminal": {
      "x": 2350,
      "y": 262,
      "w": 64,
      "h": 64
    },
    "module.bridge.emergency_control_terminal": {
      "x": 2418,
      "y": 262,
      "w": 64,
      "h": 64
    },
    "module.bridge.records_terminal": {
      "x": 2486,
      "y": 262,
      "w": 64,
      "h": 64
    },
    "module.couch": {
      "x": 2554,
      "y": 262,
      "w": 128,
      "h": 64
    },
    "module.game_station": {
      "x": 2686,
      "y": 262,
      "w": 128,
      "h": 128
    },
    "module.shower": {
      "x": 2818,
      "y": 262,
      "w": 64,
      "h": 64
    },
    "module.sink": {
      "x": 2886,
      "y": 262,
      "w": 64,
      "h": 64
    },
    "module.market_stall": {
      "x": 2,
      "y": 394,
      "w": 128,
      "h": 64
    },
    "module.intake_pallet": {
      "x": 134,
      "y": 394,
      "w": 128,
      "h": 128
    },
    "module.storage_rack": {
      "x": 266,
      "y": 394,
      "w": 128,
      "h": 64
    },
    "room.berth": {
      "x": 398,
      "y": 394,
      "w": 64,
      "h": 64
    },
    "room.cantina": {
      "x": 466,
      "y": 394,
      "w": 64,
      "h": 64
    },
    "room.observatory": {
      "x": 534,
      "y": 394,
      "w": 64,
      "h": 64
    },
    "module.gangway": {
      "x": 602,
      "y": 394,
      "w": 64,
      "h": 64
    },
    "module.customs_counter": {
      "x": 670,
      "y": 394,
      "w": 64,
      "h": 64
    },
    "module.cargo_arm": {
      "x": 738,
      "y": 394,
      "w": 128,
      "h": 128
    },
    "module.fire_extinguisher": {
      "x": 870,
      "y": 394,
      "w": 64,
      "h": 64
    },
    "module.vent": {
      "x": 938,
      "y": 394,
      "w": 64,
      "h": 64
    },
    "module.vending_machine": {
      "x": 1006,
      "y": 394,
      "w": 64,
      "h": 64
    },
    "module.bench": {
      "x": 1074,
      "y": 394,
      "w": 128,
      "h": 64
    },
    "module.bar_counter": {
      "x": 1206,
      "y": 394,
      "w": 128,
      "h": 64
    },
    "module.tap": {
      "x": 1338,
      "y": 394,
      "w": 64,
      "h": 64
    },
    "module.telescope": {
      "x": 1406,
      "y": 394,
      "w": 128,
      "h": 128
    },
    "module.water_fountain": {
      "x": 1538,
      "y": 394,
      "w": 64,
      "h": 64
    },
    "module.plant": {
      "x": 1606,
      "y": 394,
      "w": 64,
      "h": 64
    },
    "ship.tourist": {
      "x": 1674,
      "y": 394,
      "w": 64,
      "h": 64
    },
    "ship.trader": {
      "x": 1742,
      "y": 394,
      "w": 64,
      "h": 64
    },
    "ship.industrial": {
      "x": 1810,
      "y": 394,
      "w": 64,
      "h": 64
    },
    "ship.military": {
      "x": 1878,
      "y": 394,
      "w": 64,
      "h": 64
    },
    "ship.colonist": {
      "x": 1946,
      "y": 394,
      "w": 64,
      "h": 64
    },
    "overlay.dock.facade.north.solo": {
      "x": 2014,
      "y": 394,
      "w": 64,
      "h": 64
    },
    "overlay.dock.facade.north.start": {
      "x": 2082,
      "y": 394,
      "w": 64,
      "h": 64
    },
    "overlay.dock.facade.north.middle": {
      "x": 2150,
      "y": 394,
      "w": 64,
      "h": 64
    },
    "overlay.dock.facade.north.end": {
      "x": 2218,
      "y": 394,
      "w": 64,
      "h": 64
    },
    "overlay.floor.grime.1": {
      "x": 2286,
      "y": 394,
      "w": 64,
      "h": 64
    },
    "overlay.floor.grime.2": {
      "x": 2354,
      "y": 394,
      "w": 64,
      "h": 64
    },
    "overlay.floor.grime.3": {
      "x": 2422,
      "y": 394,
      "w": 64,
      "h": 64
    },
    "overlay.floor.grime.4": {
      "x": 2490,
      "y": 394,
      "w": 64,
      "h": 64
    },
    "overlay.floor.grime.5": {
      "x": 2558,
      "y": 394,
      "w": 64,
      "h": 64
    },
    "overlay.floor.grime.6": {
      "x": 2626,
      "y": 394,
      "w": 64,
      "h": 64
    },
    "overlay.floor.wear.1": {
      "x": 2694,
      "y": 394,
      "w": 64,
      "h": 64
    },
    "overlay.floor.wear.2": {
      "x": 2762,
      "y": 394,
      "w": 64,
      "h": 64
    },
    "overlay.floor.wear.3": {
      "x": 2830,
      "y": 394,
      "w": 64,
      "h": 64
    },
    "overlay.floor.wear.4": {
      "x": 2898,
      "y": 394,
      "w": 64,
      "h": 64
    },
    "agent.visitor.1": {
      "x": 2966,
      "y": 394,
      "w": 64,
      "h": 64
    },
    "agent.visitor.2": {
      "x": 2,
      "y": 526,
      "w": 64,
      "h": 64
    },
    "agent.visitor.3": {
      "x": 70,
      "y": 526,
      "w": 64,
      "h": 64
    },
    "agent.visitor.4": {
      "x": 138,
      "y": 526,
      "w": 64,
      "h": 64
    },
    "agent.visitor.5": {
      "x": 206,
      "y": 526,
      "w": 64,
      "h": 64
    },
    "agent.visitor.6": {
      "x": 274,
      "y": 526,
      "w": 64,
      "h": 64
    },
    "agent.resident.1": {
      "x": 342,
      "y": 526,
      "w": 64,
      "h": 64
    },
    "agent.resident.2": {
      "x": 410,
      "y": 526,
      "w": 64,
      "h": 64
    },
    "agent.resident.3": {
      "x": 478,
      "y": 526,
      "w": 64,
      "h": 64
    },
    "agent.resident.4": {
      "x": 546,
      "y": 526,
      "w": 64,
      "h": 64
    },
    "agent.resident.5": {
      "x": 614,
      "y": 526,
      "w": 64,
      "h": 64
    },
    "agent.resident.6": {
      "x": 682,
      "y": 526,
      "w": 64,
      "h": 64
    },
    "agent.crew.1": {
      "x": 750,
      "y": 526,
      "w": 64,
      "h": 64
    },
    "agent.crew.2": {
      "x": 818,
      "y": 526,
      "w": 64,
      "h": 64
    },
    "agent.crew.3": {
      "x": 886,
      "y": 526,
      "w": 64,
      "h": 64
    },
    "agent.crew.4": {
      "x": 954,
      "y": 526,
      "w": 64,
      "h": 64
    },
    "agent.crew.5": {
      "x": 1022,
      "y": 526,
      "w": 64,
      "h": 64
    },
    "agent.crew.6": {
      "x": 1090,
      "y": 526,
      "w": 64,
      "h": 64
    },
    "agent.crew.eva_suit": {
      "x": 1158,
      "y": 526,
      "w": 64,
      "h": 64
    },
    "agent.crew.captain": {
      "x": 1226,
      "y": 526,
      "w": 64,
      "h": 64
    },
    "agent.crew.sanitation_officer": {
      "x": 1294,
      "y": 526,
      "w": 64,
      "h": 64
    },
    "agent.crew.security_officer": {
      "x": 1362,
      "y": 526,
      "w": 64,
      "h": 64
    },
    "agent.crew.mechanic_officer": {
      "x": 1430,
      "y": 526,
      "w": 64,
      "h": 64
    },
    "agent.crew.industrial_officer": {
      "x": 1498,
      "y": 526,
      "w": 64,
      "h": 64
    },
    "agent.crew.navigation_officer": {
      "x": 1566,
      "y": 526,
      "w": 64,
      "h": 64
    },
    "agent.crew.comms_officer": {
      "x": 1634,
      "y": 526,
      "w": 64,
      "h": 64
    },
    "agent.crew.medical_officer": {
      "x": 1702,
      "y": 526,
      "w": 64,
      "h": 64
    },
    "agent.crew.eva_specialist": {
      "x": 1770,
      "y": 526,
      "w": 64,
      "h": 64
    },
    "agent.crew.eva_engineer": {
      "x": 1838,
      "y": 526,
      "w": 64,
      "h": 64
    },
    "agent.crew.flight_controller": {
      "x": 1906,
      "y": 526,
      "w": 64,
      "h": 64
    },
    "agent.crew.docking_officer": {
      "x": 1974,
      "y": 526,
      "w": 64,
      "h": 64
    },
    "agent.crew.doctor": {
      "x": 2042,
      "y": 526,
      "w": 64,
      "h": 64
    },
    "agent.crew.nurse": {
      "x": 2110,
      "y": 526,
      "w": 64,
      "h": 64
    },
    "agent.crew.cook": {
      "x": 2178,
      "y": 526,
      "w": 64,
      "h": 64
    },
    "agent.crew.cleaner": {
      "x": 2246,
      "y": 526,
      "w": 64,
      "h": 64
    },
    "agent.crew.janitor": {
      "x": 2314,
      "y": 526,
      "w": 64,
      "h": 64
    },
    "agent.crew.botanist": {
      "x": 2382,
      "y": 526,
      "w": 64,
      "h": 64
    },
    "agent.crew.technician": {
      "x": 2450,
      "y": 526,
      "w": 64,
      "h": 64
    },
    "agent.crew.assistant": {
      "x": 2518,
      "y": 526,
      "w": 64,
      "h": 64
    },
    "agent.crew.security_guard": {
      "x": 2586,
      "y": 526,
      "w": 64,
      "h": 64
    },
    "agent.crew.maintenance_tech": {
      "x": 2654,
      "y": 526,
      "w": 64,
      "h": 64
    },
    "agent.crew.engineer": {
      "x": 2722,
      "y": 526,
      "w": 64,
      "h": 64
    },
    "agent.crew.mechanic": {
      "x": 2790,
      "y": 526,
      "w": 64,
      "h": 64
    },
    "agent.crew.welder": {
      "x": 2858,
      "y": 526,
      "w": 64,
      "h": 64
    },
    "space.planet.rocky.1": {
      "x": 2,
      "y": 594,
      "w": 256,
      "h": 256
    },
    "space.asteroid.cluster.1": {
      "x": 262,
      "y": 594,
      "w": 256,
      "h": 256
    },
    "space.debris.metal.1": {
      "x": 522,
      "y": 594,
      "w": 128,
      "h": 128
    },
    "space.debris.ice.1": {
      "x": 654,
      "y": 594,
      "w": 128,
      "h": 128
    },
    "fx.repair.spark": {
      "x": 786,
      "y": 594,
      "w": 128,
      "h": 128
    },
    "overlay.wall.hull_wear.1": {
      "x": 918,
      "y": 594,
      "w": 64,
      "h": 64
    },
    "overlay.wall.hull_wear.2": {
      "x": 986,
      "y": 594,
      "w": 64,
      "h": 64
    },
    "icon.tier1_unlock": {
      "x": 1054,
      "y": 594,
      "w": 64,
      "h": 64
    },
    "icon.tier2_unlock": {
      "x": 1122,
      "y": 594,
      "w": 64,
      "h": 64
    },
    "icon.tier3_unlock": {
      "x": 1190,
      "y": 594,
      "w": 64,
      "h": 64
    },
    "icon.tier4_unlock": {
      "x": 1258,
      "y": 594,
      "w": 64,
      "h": 64
    },
    "icon.tier5_unlock": {
      "x": 1326,
      "y": 594,
      "w": 64,
      "h": 64
    },
    "icon.tier6_unlock": {
      "x": 1394,
      "y": 594,
      "w": 64,
      "h": 64
    }
  },
  "rotations": {
    "tile.wall": 90,
    "tile.wall.solo": 90,
    "tile.wall.end": 90,
    "tile.wall.straight": 90,
    "tile.wall.corner": 270,
    "tile.wall.tee": 90,
    "tile.wall.cross": 90
  },
  "offsets": {
    "overlay.dock.facade.north.solo": {
      "x": -16,
      "y": -48
    },
    "overlay.dock.facade.north.start": {
      "x": -16,
      "y": -48
    },
    "overlay.dock.facade.north.middle": {
      "x": -16,
      "y": -48
    },
    "overlay.dock.facade.north.end": {
      "x": -16,
      "y": -48
    }
  },
  "alphas": {
    "overlay.floor.grime.1": 0.18,
    "overlay.floor.grime.2": 0.18,
    "overlay.floor.grime.3": 0.18,
    "overlay.floor.grime.4": 0.18,
    "overlay.floor.grime.5": 0.18,
    "overlay.floor.grime.6": 0.18,
    "overlay.floor.wear.1": 0.24,
    "overlay.floor.wear.2": 0.24,
    "overlay.floor.wear.3": 0.24,
    "overlay.floor.wear.4": 0.24,
    "space.planet.rocky.1": 0.42,
    "space.asteroid.cluster.1": 0.52,
    "space.debris.metal.1": 0.55,
    "space.debris.ice.1": 0.5,
    "fx.repair.spark": 0.88,
    "overlay.wall.hull_wear.1": 0.48,
    "overlay.wall.hull_wear.2": 0.52
  }
}
